ExtractTable/__init__.py
ExtractTable/__version__.py
ExtractTable/common.py
ExtractTable/config.py
ExtractTable/exceptions.py
ExtractTable/parsers.py
ExtractTable/FileOperations/__init__.py
ExtractTable-2.3.1.dist-info/LICENSE
ExtractTable-2.3.1.dist-info/METADATA
ExtractTable-2.3.1.dist-info/WHEEL
ExtractTable-2.3.1.dist-info/top_level.txt
ExtractTable-2.3.1.dist-info/RECORD
