Metadata-Version: 2.1
Name: ExtractTable
Version: 2.3.1
Summary: Extract table data from images and scanned PDFs. Easily convert image to excel, convert pdf to table
Home-page: https://github.com/ExtractTable/ExtractTable-py
Author: Saradhi
Author-email: saradhi@extracttable.com
License: Apache License 2.0
Platform: UNKNOWN
Classifier: License :: OSI Approved :: Apache Software License
Classifier: Programming Language :: Python :: 3.5
Classifier: Programming Language :: Python :: 3.6
Classifier: Programming Language :: Python :: 3.7
License-File: LICENSE
Requires-Dist: requests (>=2.21)
Requires-Dist: pandas (>=0.24)
Requires-Dist: PyPDF2 (>=1.26)
